COPYING
COPYING.LESSER
MANIFEST.in
setup.py
caslib/__init__.py
caslib/cas_dance.py
caslib/test_cas_dance.py
caslib/validating_https.py
caslib.egg-info/PKG-INFO
caslib.egg-info/SOURCES.txt
caslib.egg-info/dependency_links.txt
caslib.egg-info/not-zip-safe
caslib.egg-info/requires.txt
caslib.egg-info/top_level.txt
doc/Makefile
doc/README.txt
doc/caslib.txt
doc/caslib.validating_https.txt
doc/conf.py
doc/index.txt