Metadata-Version: 1.0
Name: caslib
Version: 0.3.1
Summary: caslib provides a python interface to CAS
Home-page: http://packages.python.org/caslib/
Author: Kai Groner
Author-email: kgroner@nrao.edu
License: LGPL
Platform: UNKNOWN
Classifier: Development Status :: 3 - Alpha
Classifier: Operating System :: OS Independent
Classifier: Programming Language :: Python
Classifier: Topic :: Software Development :: Libraries :: Python Modules
Classifier: License :: OSI Approved :: GNU Library or Lesser General Public License (LGPL)
